pip_services4_http/__init__.py
pip_services4_http/auth/BasicAuthorizer.py
pip_services4_http/auth/OwnerAuthorizer.py
pip_services4_http/auth/RoleAuthorizer.py
pip_services4_http/auth/__init__.py
pip_services4_http/build/DefaultRpcFactory.py
pip_services4_http/build/__init__.py
pip_services4_http/clients/CommandableHttpClient.py
pip_services4_http/clients/RestClient.py
pip_services4_http/clients/__init__.py
pip_services4_http/connect/HttpConnectionResolver.py
pip_services4_http/connect/__init__.py
pip_services4_http/controller/AboutOperations.py
pip_services4_http/controller/CommandableHttpController.py
pip_services4_http/controller/CommandableSwaggerDocument.py
pip_services4_http/controller/HeartBeatOperations.py
pip_services4_http/controller/HeartbeatRestController.py
pip_services4_http/controller/HttpEndpoint.py
pip_services4_http/controller/HttpRequestDetector.py
pip_services4_http/controller/HttpResponseSender.py
pip_services4_http/controller/IRegisterable.py
pip_services4_http/controller/ISwaggerController.py
pip_services4_http/controller/RestController.py
pip_services4_http/controller/RestOperations.py
pip_services4_http/controller/RestQueryParams.py
pip_services4_http/controller/SSLCherryPyServer.py
pip_services4_http/controller/StatusOperations.py
pip_services4_http/controller/StatusRestController.py
pip_services4_http/controller/__init__.py
pip_services4_http/test/TestCommandableHttpClient.py
pip_services4_http/test/TestRestClient.py
pip_services4_http/test/__init__.py
pip_services4_http-0.0.4.dist-info/LICENSE
pip_services4_http-0.0.4.dist-info/METADATA
pip_services4_http-0.0.4.dist-info/WHEEL
pip_services4_http-0.0.4.dist-info/top_level.txt
pip_services4_http-0.0.4.dist-info/zip-safe
pip_services4_http-0.0.4.dist-info/RECORD
